quiq/__init__.py
quiq/evaluate.py
quiq/test.py
quiq/test_case.py
quiq-0.0.1.dist-info/LICENSE.txt
quiq-0.0.1.dist-info/METADATA
quiq-0.0.1.dist-info/WHEEL
quiq-0.0.1.dist-info/top_level.txt
quiq-0.0.1.dist-info/RECORD
