Metadata-Version: 2.1
Name: quiq
Version: 0.0.1
Summary: A simple and lightweight TDD unit testing framework.
Home-page: https://github.com/dingelsz/quiq
Author: Zachary Dingels
Author-email: dingelsz3@gmail.com
License: GNU GPL3
Platform: UNKNOWN
Classifier: Programming Language :: Python :: 3
Classifier: License :: OSI Approved :: MIT License
Classifier: Operating System :: OS Independent
Requires-Python: >=3.6
